erpbrasil.transmissao-1.1.0-nspkg.pth
erpbrasil/monkey_patch/__init__.py
erpbrasil/monkey_patch/zeep_monkey_patch.py
erpbrasil/transmissao/__init__.py
erpbrasil/transmissao/__main__.py
erpbrasil/transmissao/cli.py
erpbrasil/transmissao/transmissao.py
erpbrasil.transmissao-1.1.0.dist-info/AUTHORS.rst
erpbrasil.transmissao-1.1.0.dist-info/LICENSE
erpbrasil.transmissao-1.1.0.dist-info/METADATA
erpbrasil.transmissao-1.1.0.dist-info/WHEEL
erpbrasil.transmissao-1.1.0.dist-info/entry_points.txt
erpbrasil.transmissao-1.1.0.dist-info/namespace_packages.txt
erpbrasil.transmissao-1.1.0.dist-info/top_level.txt
erpbrasil.transmissao-1.1.0.dist-info/RECORD
