Metadata-Version: 2.1
Name: erpbrasil.transmissao
Version: 1.1.0
Summary: Infraestrutura de transmissao de documentos eletronicos
Home-page: https://github.com/erpbrasil/erpbrasil.transmissao
Author: Luis Felipe Mileo
Author-email: mileo@kmee.com.br
License: MIT
Project-URL: Documentation, https://erpbrasiltransmissao.readthedocs.io/
Project-URL: Changelog, https://erpbrasiltransmissao.readthedocs.io/en/latest/changelog.html
Project-URL: Issue Tracker, https://github.com/erpbrasil/erpbrasil.transmissao/issues
Platform: UNKNOWN
Classifier: Development Status :: 5 - Production/Stable
Classifier: Intended Audience :: Developers
Classifier: License :: OSI Approved :: MIT License
Classifier: Operating System :: Unix
Classifier: Operating System :: POSIX
Classifier: Operating System :: Microsoft :: Windows
Classifier: Programming Language :: Python
Classifier: Programming Language :: Python :: 3
Classifier: Programming Language :: Python :: 3.5
Classifier: Programming Language :: Python :: 3.6
Classifier: Programming Language :: Python :: 3.7
Classifier: Programming Language :: Python :: Implementation :: CPython
Classifier: Programming Language :: Python :: Implementation :: PyPy
Classifier: Topic :: Utilities
Requires-Python: >=3.5, !=2.*, !=3.0.*, !=3.1.*, !=3.2.*, !=3.3.*
License-File: LICENSE
License-File: AUTHORS.rst
